{
    "@context": [
        "https://www.w3.org/ns/did/v1",
        "https://w3id.org/security/suites/jws-2020/v1"
    ],
    "id": "did:web:chrisae13.github.io",
    "verificationMethod": [
        {
            "id": "did:web:chrisae13.github.io#mTwO0nGmX-fpi1-PVthwLxd5UJkXE58RCDUE8a5Wf9c",
            "type": "JsonWebKey2020",
            "controller": "did:web:chrisae13.github.io",
            "publicKeyJwk": {
                "kty": "EC",
                "crv": "P-256",
                "kid": "mTwO0nGmX-fpi1-PVthwLxd5UJkXE58RCDUE8a5Wf9c",
                "x": "2NcIzHPczlMRsDl3MjLSIBC_VTD2xhHTAGr-Jlyspuo",
                "y": "-CDejVB5ZsBuW0i6j0r13IXFDIERulhQ4Zp4NBe2jU8"
            }
        }
    ],
    "assertionMethod": [
        "did:web:chrisae13.github.io#mTwO0nGmX-fpi1-PVthwLxd5UJkXE58RCDUE8a5Wf9c"
    ],
    "authentication": [
        "did:web:chrisae13.github.io#mTwO0nGmX-fpi1-PVthwLxd5UJkXE58RCDUE8a5Wf9c"
    ],
    "capabilityInvocation": [
        "did:web:chrisae13.github.io#mTwO0nGmX-fpi1-PVthwLxd5UJkXE58RCDUE8a5Wf9c"
    ],
    "capabilityDelegation": [
        "did:web:chrisae13.github.io#mTwO0nGmX-fpi1-PVthwLxd5UJkXE58RCDUE8a5Wf9c"
    ],
    "keyAgreement": [
        "did:web:chrisae13.github.io#mTwO0nGmX-fpi1-PVthwLxd5UJkXE58RCDUE8a5Wf9c"
    ]
}